MANIFEST.in
README.md
setup.cfg
setup.py
pims_nd2/ND2SDK.py
pims_nd2/__init__.py
pims_nd2/cluster.nd2
pims_nd2/nd2reader.py
pims_nd2/test.py
pims_nd2.egg-info/PKG-INFO
pims_nd2.egg-info/SOURCES.txt
pims_nd2.egg-info/dependency_links.txt
pims_nd2.egg-info/pbr.json
pims_nd2.egg-info/requires.txt
pims_nd2.egg-info/top_level.txt
pims_nd2/ND2SDK/license.txt
pims_nd2/ND2SDK/linux/libnd2ReadSDK.so
pims_nd2/ND2SDK/linux/nd2ReadSDK.h
pims_nd2/ND2SDK/osx/ReadMe.txt
pims_nd2/ND2SDK/osx/nd2ReadSDK.h
pims_nd2/ND2SDK/osx/nd2sdk.framework/Headers
pims_nd2/ND2SDK/osx/nd2sdk.framework/Resources
pims_nd2/ND2SDK/osx/nd2sdk.framework/libjpeg.dylib
pims_nd2/ND2SDK/osx/nd2sdk.framework/libkdu_v43R.dylib
pims_nd2/ND2SDK/osx/nd2sdk.framework/libtif.dylib
pims_nd2/ND2SDK/osx/nd2sdk.framework/nd2sdk
pims_nd2/ND2SDK/osx/nd2sdk.framework/Versions/Current
pims_nd2/ND2SDK/osx/nd2sdk.framework/Versions/1/libjpeg.dylib
pims_nd2/ND2SDK/osx/nd2sdk.framework/Versions/1/libkdu_v43R.dylib
pims_nd2/ND2SDK/osx/nd2sdk.framework/Versions/1/libtif.dylib
pims_nd2/ND2SDK/osx/nd2sdk.framework/Versions/1/nd2sdk
pims_nd2/ND2SDK/osx/nd2sdk.framework/Versions/1/Headers/._nd2ReadSDK.h
pims_nd2/ND2SDK/osx/nd2sdk.framework/Versions/1/Headers/nd2ReadSDK.h
pims_nd2/ND2SDK/osx/nd2sdk.framework/Versions/1/Resources/Info.plist
pims_nd2/ND2SDK/win/ReadMe.txt
pims_nd2/ND2SDK/win/nd2ReadSDK.h
pims_nd2/ND2SDK/win/x64/LIBTIFF400_64_R.DLL
pims_nd2/ND2SDK/win/x64/kdu_v52R.dll
pims_nd2/ND2SDK/win/x64/v6_gnr_imageformat_jp2.dll
pims_nd2/ND2SDK/win/x64/v6_gnr_imageformat_nd2.dll
pims_nd2/ND2SDK/win/x64/v6_gnr_imageformat_tif.dll
pims_nd2/ND2SDK/win/x64/v6_gnr_imageformatmanager.dll
pims_nd2/ND2SDK/win/x64/v6_gnr_math.dll
pims_nd2/ND2SDK/win/x64/v6_gnr_metaformats.dll
pims_nd2/ND2SDK/win/x64/v6_gnr_picture.dll
pims_nd2/ND2SDK/win/x64/v6_gnr_system.dll
pims_nd2/ND2SDK/win/x64/v6_w32_nd2ReadSDK.dll
pims_nd2/ND2SDK/win/x64/v6_w32_pthreadVC.dll
pims_nd2/ND2SDK/win/x64/v6_w32_system.dll
pims_nd2/ND2SDK/win/x64/zlib_v123.dll
pims_nd2/ND2SDK/win/x86/LIBTIFF400_R.DLL
pims_nd2/ND2SDK/win/x86/kdu_v52R.dll
pims_nd2/ND2SDK/win/x86/v6_gnr_imageformat_jp2.dll
pims_nd2/ND2SDK/win/x86/v6_gnr_imageformat_nd2.dll
