Metadata-Version: 1.1
Name: pims-nd2
Version: 1.1
Summary: An image reader for nd2 (NIS Elements) multidimensional images
Home-page: https://github.com/soft-matter/pims_nd2
Author: Casper van der Wel
Author-email: caspervdw@gmail.com
License: UNKNOWN
Platform: MacOS X
Platform: Windows
Platform: Linux CentOs 6.5/7
Platform: Linux Debian 7/8
Classifier: Development Status :: 5 - Production/Stable
Classifier: Intended Audience :: Science/Research
Classifier: Programming Language :: C
Classifier: Programming Language :: Python
Classifier: Programming Language :: Python :: 2
Classifier: Programming Language :: Python :: 3
Classifier: Topic :: Scientific/Engineering
Classifier: Operating System :: Microsoft :: Windows
Classifier: Operating System :: POSIX
Classifier: Operating System :: Unix
Classifier: Operating System :: MacOS
